<?xml version="1.0" encoding="UTF-8"?>
<diagramme>
	<utilisateur>
		<mel>toto@toto.fr</mel>
		<information>
			<prenom>Monsieur</prenom>
			<nom>Toto</nom>
			<mdp>toto</mdp>
		</information>
	</utilisateur>
	<utilisateur>
		<mel>eldoran.s.e@gmail.com</mel>
		<information>
			<prenom>Michaël</prenom>
			<nom>Dubuis</nom>
			<mdp>0000</mdp>
		</information>
	</utilisateur>
	<utilisateur>
		<mel>ma@gmail.com</mel>
		<information>
			<prenom>Marie</prenom>
			<nom>Antoinette</nom>
			<mdp>0000</mdp>
		</information>
	</utilisateur>
</diagramme>